<?xml version="1.0" encoding="utf-8" ?>
<dwsync>
<file name="Memcache.php" server="222.122.52.20//usr/local/infra911/IoT_ENERGY/" local="131327232730000000" remote="131327232730000000" Dst="0" />
<file name="Igbinary.php" server="222.122.52.20//usr/local/infra911/IoT_ENERGY/" local="131327232730000000" remote="131327232730000000" Dst="0" />
<file name="Memory.php" server="222.122.52.20//usr/local/infra911/IoT_ENERGY/" local="131327232730000000" remote="131327232730000000" Dst="0" />
<file name="SQLite.php" server="222.122.52.20//usr/local/infra911/IoT_ENERGY/" local="131327232740000000" remote="131327232740000000" Dst="0" />
<file name="PHPTemp.php" server="222.122.52.20//usr/local/infra911/IoT_ENERGY/" local="131327232730000000" remote="131327232730000000" Dst="0" />
<file name="ICache.php" server="222.122.52.20//usr/local/infra911/IoT_ENERGY/" local="131327232730000000" remote="131327232730000000" Dst="0" />
<file name="APC.php" server="222.122.52.20//usr/local/infra911/IoT_ENERGY/" local="131327232730000000" remote="131327232730000000" Dst="0" />
<file name="Wincache.php" server="222.122.52.20//usr/local/infra911/IoT_ENERGY/" local="131327232740000000" remote="131327232740000000" Dst="0" />
<file name="MemorySerialized.php" server="222.122.52.20//usr/local/infra911/IoT_ENERGY/" local="131327232730000000" remote="131327232730000000" Dst="0" />
<file name="DiscISAM.php" server="222.122.52.20//usr/local/infra911/IoT_ENERGY/" local="131327232730000000" remote="131327232730000000" Dst="0" />
<file name="CacheBase.php" server="222.122.52.20//usr/local/infra911/IoT_ENERGY/" local="131327232730000000" remote="131327232730000000" Dst="0" />
<file name="SQLite3.php" server="222.122.52.20//usr/local/infra911/IoT_ENERGY/" local="131327232740000000" remote="131327232740000000" Dst="0" />
<file name="MemoryGZip.php" server="222.122.52.20//usr/local/infra911/IoT_ENERGY/" local="131327232730000000" remote="131327232730000000" Dst="0" />
<file name="SQLite3.php" server="123.108.176.24:2722//usr/local/infra911/NOTUSE_DISCOUNT/" local="131327232740000000" remote="131363581290000000" Dst="0" />
<file name="Memcache.php" server="123.108.176.24:2722//usr/local/infra911/NOTUSE_DISCOUNT/" local="131327232730000000" remote="131363581290000000" Dst="0" />
<file name="Igbinary.php" server="123.108.176.24:2722//usr/local/infra911/NOTUSE_DISCOUNT/" local="131327232730000000" remote="131363581290000000" Dst="0" />
<file name="Wincache.php" server="123.108.176.24:2722//usr/local/infra911/NOTUSE_DISCOUNT/" local="131327232740000000" remote="131363581290000000" Dst="0" />
<file name="Memory.php" server="123.108.176.24:2722//usr/local/infra911/NOTUSE_DISCOUNT/" local="131327232730000000" remote="131363581290000000" Dst="0" />
<file name="DiscISAM.php" server="123.108.176.24:2722//usr/local/infra911/NOTUSE_DISCOUNT/" local="131327232730000000" remote="131363581290000000" Dst="0" />
<file name="SQLite.php" server="123.108.176.24:2722//usr/local/infra911/NOTUSE_DISCOUNT/" local="131327232740000000" remote="131363581290000000" Dst="0" />
<file name="APC.php" server="123.108.176.24:2722//usr/local/infra911/NOTUSE_DISCOUNT/" local="131327232730000000" remote="131363581290000000" Dst="0" />
<file name="MemoryGZip.php" server="123.108.176.24:2722//usr/local/infra911/NOTUSE_DISCOUNT/" local="131327232730000000" remote="131363581290000000" Dst="0" />
<file name="ICache.php" server="123.108.176.24:2722//usr/local/infra911/NOTUSE_DISCOUNT/" local="131327232730000000" remote="131363581290000000" Dst="0" />
<file name="MemorySerialized.php" server="123.108.176.24:2722//usr/local/infra911/NOTUSE_DISCOUNT/" local="131327232730000000" remote="131363581290000000" Dst="0" />
<file name="PHPTemp.php" server="123.108.176.24:2722//usr/local/infra911/NOTUSE_DISCOUNT/" local="131327232730000000" remote="131363581290000000" Dst="0" />
<file name="CacheBase.php" server="123.108.176.24:2722//usr/local/infra911/NOTUSE_DISCOUNT/" local="131327232730000000" remote="131363581290000000" Dst="0" />
<file name="SQLite3.php" server="123.108.176.28//usr/local/infra911/SMARTBUS/" local="131327232740000000" remote="131477709030000000" Dst="0" />
<file name="Memcache.php" server="123.108.176.28//usr/local/infra911/SMARTBUS/" local="131327232730000000" remote="131477709030000000" Dst="0" />
<file name="Igbinary.php" server="123.108.176.28//usr/local/infra911/SMARTBUS/" local="131327232730000000" remote="131477709030000000" Dst="0" />
<file name="Wincache.php" server="123.108.176.28//usr/local/infra911/SMARTBUS/" local="131327232740000000" remote="131477709030000000" Dst="0" />
<file name="Memory.php" server="123.108.176.28//usr/local/infra911/SMARTBUS/" local="131327232730000000" remote="131477709030000000" Dst="0" />
<file name="DiscISAM.php" server="123.108.176.28//usr/local/infra911/SMARTBUS/" local="131327232730000000" remote="131477709040000000" Dst="0" />
<file name="SQLite.php" server="123.108.176.28//usr/local/infra911/SMARTBUS/" local="131327232740000000" remote="131477709040000000" Dst="0" />
<file name="APC.php" server="123.108.176.28//usr/local/infra911/SMARTBUS/" local="131327232730000000" remote="131477709040000000" Dst="0" />
<file name="MemoryGZip.php" server="123.108.176.28//usr/local/infra911/SMARTBUS/" local="131327232730000000" remote="131477709040000000" Dst="0" />
<file name="ICache.php" server="123.108.176.28//usr/local/infra911/SMARTBUS/" local="131327232730000000" remote="131477709040000000" Dst="0" />
<file name="MemorySerialized.php" server="123.108.176.28//usr/local/infra911/SMARTBUS/" local="131327232730000000" remote="131477709040000000" Dst="0" />
<file name="PHPTemp.php" server="123.108.176.28//usr/local/infra911/SMARTBUS/" local="131327232730000000" remote="131477709040000000" Dst="0" />
<file name="CacheBase.php" server="123.108.176.28//usr/local/infra911/SMARTBUS/" local="131327232730000000" remote="131477709040000000" Dst="0" />
</dwsync>